moulti/__init__.py
moulti/__main__.py
moulti/ansi.py
moulti/app.py
moulti/askpass.py
moulti/cli.py
moulti/client.py
moulti/clipboard.py
moulti/diff.py
moulti/environ.py
moulti/helpers.py
moulti/manpage.py
moulti/pipeline.py
moulti/precli.py
moulti/protocol.py
moulti/search.py
moulti/security.py
moulti/server.py
moulti/themes.py
moulti/thread_name.py
moulti/ansible/__init__.py
moulti/ansible/moulti.py
moulti/widgets/__init__.py
moulti/widgets/cli.py
moulti/widgets/footer.py
moulti/widgets/helpscreen.py
moulti/widgets/mixin.py
moulti/widgets/moulticonsole.py
moulti/widgets/moultilog.py
moulti/widgets/quitdialog.py
moulti/widgets/searchinput.py
moulti/widgets/stepcontainer.py
moulti/widgets/tui.py
moulti/widgets/vertscroll.py
moulti/widgets/abstractquestion/__init__.py
moulti/widgets/abstractquestion/cli.py
moulti/widgets/abstractquestion/tui.py
moulti/widgets/abstractstep/__init__.py
moulti/widgets/abstractstep/cli.py
moulti/widgets/abstractstep/tui.py
moulti/widgets/buttonquestion/__init__.py
moulti/widgets/buttonquestion/cli.py
moulti/widgets/buttonquestion/tui.py
moulti/widgets/collapsiblestep/__init__.py
moulti/widgets/collapsiblestep/cli.py
moulti/widgets/collapsiblestep/tui.py
moulti/widgets/divider/__init__.py
moulti/widgets/divider/cli.py
moulti/widgets/divider/tui.py
moulti/widgets/inputquestion/__init__.py
moulti/widgets/inputquestion/cli.py
moulti/widgets/inputquestion/tui.py
moulti/widgets/question/__init__.py
moulti/widgets/question/cli.py
moulti/widgets/question/tui.py
moulti/widgets/step/__init__.py
moulti/widgets/step/cli.py
moulti/widgets/step/tui.py
moulti-1.34.1.data/scripts/moulti-functions.bash
moulti-1.34.1.data/scripts/moulti-man
moulti-1.34.1.dist-info/licenses/LICENSE
moulti-1.34.1.dist-info/METADATA
moulti-1.34.1.dist-info/WHEEL
moulti-1.34.1.dist-info/entry_points.txt
moulti-1.34.1.dist-info/top_level.txt
moulti-1.34.1.dist-info/RECORD
