Metadata-Version: 2.4
Name: moulti
Version: 1.34.1
Summary: Moulti is a CLI-driven Terminal User Interface (TUI) displaying arbitrary outputs inside visual, collapsible blocks called steps.
Author-email: "Xavier G." <xavier.moulti@kindwolf.org>
License: MIT License
Project-URL: Homepage, https://moulti.run/
Project-URL: Documentation, https://moulti.run/
Project-URL: Repository, https://github.com/xavierog/moulti.git
Project-URL: Issues, https://github.com/xavierog/moulti/issues
Project-URL: Changelog, https://github.com/xavierog/moulti/blob/master/CHANGELOG.md
Keywords: ansible,cli,collapsible,curses,diff,multiplex,output,script,steps,terminal,textual,tui
Classifier: Environment :: Console :: Curses
Classifier: Intended Audience :: Developers
Classifier: Intended Audience :: System Administrators
Classifier: License :: OSI Approved :: MIT License
Classifier: Operating System :: MacOS :: MacOS X
Classifier: Operating System :: POSIX :: BSD :: FreeBSD
Classifier: Operating System :: POSIX :: BSD :: NetBSD
Classifier: Operating System :: POSIX :: BSD :: OpenBSD
Classifier: Operating System :: POSIX :: Linux
Classifier: Programming Language :: Python :: 3 :: Only
Classifier: Topic :: System :: Logging
Classifier: Topic :: Utilities
Requires-Python: >=3.10
License-File: LICENSE
Requires-Dist: argcomplete
Requires-Dist: pyperclip
Requires-Dist: textual==1.0.*
Requires-Dist: unidiff
Provides-Extra: tinker
Requires-Dist: bpython; extra == "tinker"
Requires-Dist: textual-dev; extra == "tinker"
Provides-Extra: check-py
Requires-Dist: mypy; extra == "check-py"
Requires-Dist: pylint; extra == "check-py"
Provides-Extra: check-rust
Requires-Dist: ruff; extra == "check-rust"
Provides-Extra: check
Requires-Dist: moulti[check-py,check-rust]; extra == "check"
Provides-Extra: test
Requires-Dist: pytest; extra == "test"
Requires-Dist: pytest-asyncio; extra == "test"
Requires-Dist: pytest-forked; extra == "test"
Requires-Dist: pytest-textual-snapshot; extra == "test"
Requires-Dist: pytest-xdist; extra == "test"
Provides-Extra: release
Requires-Dist: build; extra == "release"
Requires-Dist: twine; extra == "release"
Provides-Extra: doc
Requires-Dist: mkdocs-material[imaging]; extra == "doc"
Requires-Dist: mkdocs-inline-select-svg-plugin; extra == "doc"
Provides-Extra: dev
Requires-Dist: moulti[check,doc,release,test,tinker]; extra == "dev"
Provides-Extra: ci
Requires-Dist: moulti[check,test]; extra == "ci"
Provides-Extra: bsd-ci
Requires-Dist: moulti[check-py,test]; extra == "bsd-ci"
Dynamic: license-file
